pyriemann/__init__.py
pyriemann/_base.py
pyriemann/_version.py
pyriemann/channelselection.py
pyriemann/classification.py
pyriemann/clustering.py
pyriemann/embedding.py
pyriemann/estimation.py
pyriemann/preprocessing.py
pyriemann/regression.py
pyriemann/spatialfilters.py
pyriemann/stats.py
pyriemann/tangentspace.py
pyriemann/datasets/__init__.py
pyriemann/datasets/sampling.py
pyriemann/datasets/simulated.py
pyriemann/optimization/__init__.py
pyriemann/optimization/grassmann.py
pyriemann/optimization/positive_definite.py
pyriemann/transfer/__init__.py
pyriemann/transfer/_estimators.py
pyriemann/transfer/_tools.py
pyriemann/utils/__init__.py
pyriemann/utils/_logging.py
pyriemann/utils/ajd.py
pyriemann/utils/base.py
pyriemann/utils/covariance.py
pyriemann/utils/distance.py
pyriemann/utils/docs.py
pyriemann/utils/geodesic.py
pyriemann/utils/kernel.py
pyriemann/utils/mean.py
pyriemann/utils/median.py
pyriemann/utils/tangentspace.py
pyriemann/utils/test.py
pyriemann/utils/utils.py
pyriemann/utils/viz.py
pyriemann-0.10.dist-info/licenses/LICENSE
pyriemann-0.10.dist-info/METADATA
pyriemann-0.10.dist-info/WHEEL
pyriemann-0.10.dist-info/top_level.txt
pyriemann-0.10.dist-info/RECORD
