Metadata-Version: 2.4
Name: pyriemann
Version: 0.10
Summary: Machine learning for multivariate data with Riemannian geometry
Home-page: https://pyriemann.readthedocs.io
Author: Alexandre Barachant
Author-email: alexandre.barachant@gmail.com
License: BSD (3-clause)
Project-URL: Documentation, https://pyriemann.readthedocs.io
Project-URL: Source, https://github.com/pyRiemann/pyRiemann
Project-URL: Tracker, https://github.com/pyRiemann/pyRiemann/issues/
Platform: any
Requires-Python: >=3.9
License-File: LICENSE
Requires-Dist: numpy>=1.25.0
Requires-Dist: scipy
Requires-Dist: scikit-learn>=0.24
Requires-Dist: joblib
Requires-Dist: matplotlib
Provides-Extra: docs
Requires-Dist: sphinx; extra == "docs"
Requires-Dist: sphinx-gallery; extra == "docs"
Requires-Dist: sphinx-bootstrap_theme; extra == "docs"
Requires-Dist: numpydoc; extra == "docs"
Requires-Dist: mne; extra == "docs"
Requires-Dist: seaborn; extra == "docs"
Requires-Dist: pandas; extra == "docs"
Provides-Extra: tests
Requires-Dist: pytest; extra == "tests"
Requires-Dist: seaborn; extra == "tests"
Requires-Dist: flake8; extra == "tests"
Dynamic: author
Dynamic: author-email
Dynamic: description
Dynamic: description-content-type
Dynamic: home-page
Dynamic: license
Dynamic: license-file
Dynamic: platform
Dynamic: project-url
Dynamic: provides-extra
Dynamic: requires-dist
Dynamic: requires-python
Dynamic: summary
